{
  "JPM": "2026-01-13",
  "BAC": "2026-01-14",
  "C": "2026-01-14",
  "WFC": "2026-01-14",
  "BK": "2026-01-15",
  "GS": "2026-01-15",
  "MS": "2026-01-15",
  "MTB": "2026-01-16",
  "PNC": "2026-01-16",
  "KEY": "2026-01-20",
  "USB": "2026-01-20",
  "CFG": "2026-01-21",
  "SCHW": "2026-01-21",
  "HAL": "2026-01-21",
  "FITB": "2026-01-22",
  "NTRS": "2026-01-22",
  "GE": "2026-01-22",
  "SLB": "2026-01-23",
  "SNA": "2026-01-23",
  "NOC": "2026-01-27",
  "RTX": "2026-01-27",
  "UNP": "2026-01-27",
  "UPS": "2026-01-27",
  "TXN": "2026-01-27",
  "NEE": "2026-01-27",
  "LRCX": "2026-01-28",
  "KLAC": "2026-01-29",
  "WDC": "2026-01-29",
  "STX": "2026-01-29",
  "CAT": "2026-01-29",
  "HON": "2026-01-29",
  "LMT": "2026-01-29",
  "VLO": "2026-01-29",
  "TMO": "2026-01-29",
  "AXP": "2026-01-30",
  "CVX": "2026-01-30",
  "XOM": "2026-01-30",
  "PSX": "2026-01-30",
  "SNDK": "2026-01-30",
  "HIG": "2026-01-30",
  "ETN": "2026-02-03",
  "ITW": "2026-02-03",
  "MPC": "2026-02-03",
  "ON": "2026-02-03",
  "PYPL": "2026-02-04",
  "WAT": "2026-02-04",
  "COP": "2026-02-05",
  "ACGL": "2026-02-05",
  "CTSH": "2026-02-05",
  "CDW": "2026-02-05",
  "BAX": "2026-02-06",
  "CI": "2026-02-06",
  "CNP": "2026-02-06",
  "FTV": "2026-02-06",
  "HAS": "2026-02-10",
  "PLTR": "2026-02-10",
  "DUK": "2026-02-10",
  "WMB": "2026-02-10",
  "WAB": "2026-02-11",
  "AEE": "2026-02-12",
  "APP": "2026-02-12",
  "COIN": "2026-02-13",
  "EPAM": "2026-02-13",
  "DTE": "2026-02-13",
  "LNT": "2026-02-13",
  "PPL": "2026-02-13",
  "DLR": "2026-02-13",
  "IRM": "2026-02-13",
  "CDNS": "2026-02-17",
  "DVN": "2026-02-17",
  "OXY": "2026-02-18",
  "FE": "2026-02-19",
  "NI": "2026-02-19",
  "NTAP": "2026-02-19",
  "SO": "2026-02-19",
  "EVRG": "2026-02-20",
  "EOG": "2026-02-24",
  "OKE": "2026-02-23",
  "SBUX": "2026-01-28",
  "FDX": "2025-12-18",
  "MU": "2025-12-17"
}
